multiflow/__init__.py
multiflow_python-0.0.8.dist-info/LICENSE
multiflow_python-0.0.8.dist-info/METADATA
multiflow_python-0.0.8.dist-info/WHEEL
multiflow_python-0.0.8.dist-info/top_level.txt
multiflow_python-0.0.8.dist-info/RECORD
