Metadata-Version: 2.1
Name: multiflow-python
Version: 0.0.8
Summary: MultiFlow Python SDK
Author-email: "Multi Technologies Inc." <hello@llm.llc>
License: MIT License
Requires-Python: >=3.8
License-File: LICENSE
Requires-Dist: fire
Requires-Dist: requests
Requires-Dist: dacite
Requires-Dist: asyncio
Requires-Dist: aiohttp
